{"id_pessoa":"sf7Ly18mCYcQa2lF","valor":10,"data":"05/10/2019","carro":"saveiro","dias":"15","valor_dolar":39.30802,"_id":"JTwB9EaTEeoCplQM"}
{"id_pessoa":"sf7Ly18mCYcQa2lF","valor":1,"data":"05/10/2019","carro":"gol","dias":"20","valor_dolar":3.930802,"_id":"Np0FS3DapbGKCPor"}
{"id_pessoa":"sf7Ly18mCYcQa2lF","valor":10,"data":"05/10/2019","carro":"saveiro","dias":"15","valor_dolar":39.76198,"_id":"SeuaE9idaNvU9n0W"}
{"id_pessoa":"sf7Ly18mCYcQa2lF","valor":1,"data":"10/10/2019","carro":"fox","dias":"20","valor_dolar":3.930802,"_id":"jOSWPjZ5LHDntyVS"}
